Workbook

Sheet Übersicht
C1: 46112 | D1: =EOMONTH(C1,1) -> 46142 | E1: =EOMONTH(D1,1) -> 46173 | F1: =EOMONTH(E1,1) -> 46203 | G1: =EOMONTH(F1,1) -> 46234 | H1: =EOMONTH(G1,1) -> 46265 | I1: =EOMONTH(H1,1) -> 46295 | J1: =EOMONTH(I1,1) -> 46326 | K1: =EOMONTH(J1,1) -> 46356 | ... AL1: =EOMONTH(AK1,1) -> 47177
A3: Revenue | C3: =SUM(C4,C5,C7) -> 220 | D3: =SUM(D4,D5,D7) -> 340 | E3: =SUM(E4,E5,E7) -> 560 | F3: =SUM(F4,F5,F7) -> 3880 | G3: =SUM(G4,G5,G7) -> 4220 | H3: =SUM(H4,H5,H7) -> 4560 | I3: =SUM(I4,I5,I7) -> 5020 | J3: =SUM(J4,J5,J7) -> 5400 | ... AL3: =SUM(AL4,AL5,AL7) -> 45640
B4: Paid | C4: =Umsatz!D16 -> 120 | D4: =Umsatz!E16 -> 240 | E4: =Umsatz!F16 -> 360 | F4: =Umsatz!G16 -> 580 | G4: =Umsatz!H16 -> 820 | H4: =Umsatz!I16 -> 1060 | I4: =Umsatz!J16 -> 1320 | J4: =Umsatz!K16 -> 1600 | ... AL4: =Umsatz!AM16 -> 28440
B5: Premium | C5: =Umsatz!D23 -> 100 | D5: =Umsatz!E23 -> 100 | E5: =Umsatz!F23 -> 200 | F5: =Umsatz!G23 -> 300 | G5: =Umsatz!H23 -> 400 | H5: =Umsatz!I23 -> 500 | I5: =Umsatz!J23 -> 700 | J5: =Umsatz!K23 -> 800 | ... AL5: =Umsatz!AM23 -> 14200
B7: Consulting | C7: =Umsatz!D28 -> 0 | D7: =Umsatz!E28 -> 0 | E7: =Umsatz!F28 -> 0 | F7: =Umsatz!G28 -> 3000 | G7: =Umsatz!H28 -> 3000 | H7: =Umsatz!I28 -> 3000 | I7: =Umsatz!J28 -> 3000 | J7: =Umsatz!K28 -> 3000 | ... AL7: =Umsatz!AM28 -> 3000
A9: Kosten | C9: =Kosten!E3 -> -1909 | D9: =Kosten!F3 -> -1636 | E9: =Kosten!G3 -> -1796 | F9: =Kosten!H3 -> -1986 | G9: =Kosten!I3 -> -2210 | H9: =Kosten!J3 -> -2516 | I9: =Kosten!K3 -> -2738 | J9: =Kosten!L3 -> -2918 | ... AL9: =Kosten!AN3 -> -26406
B10: Growth | C10: =Kosten!E41 -> -40 | D10: =Kosten!F41 -> -40 | E10: =Kosten!G41 -> -40 | F10: =Kosten!H41 -> -40 | G10: =Kosten!I41 -> -40 | H10: =Kosten!J41 -> -40 | I10: =Kosten!K41 -> -40 | J10: =Kosten!L41 -> -40 | ... AL10: =Kosten!AN41 -> -40
B12: Variable Kosten | C12: =SUM(C13:C14) -> -258 | D12: =SUM(D13:D14) -> -366 | E12: =SUM(E13:E14) -> -526 | F12: =SUM(F13:F14) -> -716 | G12: =SUM(G13:G14) -> -940 | H12: =SUM(H13:H14) -> -1246 | I12: =SUM(I13:I14) -> -1468 | J12: =SUM(J13:J14) -> -1648 | ... T12: =SUM(T13:T14) -> -4446
B13: Variable Operative | C13: =Kosten!E5 -> -158 | D13: =Kosten!F5 -> -266 | E13: =Kosten!G5 -> -426 | F13: =Kosten!H5 -> -616 | G13: =Kosten!I5 -> -820 | H13: =Kosten!J5 -> -1026 | I13: =Kosten!K5 -> -1248 | J13: =Kosten!L5 -> -1428 | ... AL13: =Kosten!AN5 -> -22016
B14: IT Operations | C14: =Kosten!E23 -> -100 | D14: =Kosten!F23 -> -100 | E14: =Kosten!G23 -> -100 | F14: =Kosten!H23 -> -100 | G14: =Kosten!I23 -> -120 | H14: =Kosten!J23 -> -220 | I14: =Kosten!K23 -> -220 | J14: =Kosten!L23 -> -220 | ... AL14: =Kosten!AN23 -> -220
B16: Fixkosten | C16: =SUM(C13:C15) -> -258 | D16: =SUM(D13:D15) -> -366 | E16: =SUM(E13:E15) -> -526 | F16: =SUM(F13:F15) -> -716 | G16: =SUM(G13:G15) -> -940 | H16: =SUM(H13:H15) -> -1246 | I16: =SUM(I13:I15) -> -1468 | J16: =SUM(J13:J15) -> -1648 | ... T16: =SUM(T13:T15) -> -4446
B17: =Kosten!A16 -> Produktentwicklung | C17: =Kosten!E16 -> -1200 | D17: =Kosten!F16 -> -1200 | E17: =Kosten!G16 -> -1200 | F17: =Kosten!H16 -> -1200 | G17: =Kosten!I16 -> -1200 | H17: =Kosten!J16 -> -1200 | I17: =Kosten!K16 -> -1200 | J17: =Kosten!L16 -> -1200 | ... AL17: =Kosten!AN16
B18: =Kosten!A27 -> Administrative Kosten | C18: =Kosten!E27 -> -411 | D18: =Kosten!F27 -> -30 | E18: =Kosten!G27 -> -30 | F18: =Kosten!H27 -> -30 | G18: =Kosten!I27 -> -30 | H18: =Kosten!J27 -> -30 | I18: =Kosten!K27 -> -30 | J18: =Kosten!L27 -> -30 | ... AL18: =Kosten!AN27 -> -4130
B20: Fixkosten
A23: Operatives Ergebnis | C23: =C3+C9 -> -1689 | D23: =D3+D9 -> -1296 | E23: =E3+E9 -> -1236 | F23: =F3+F9 -> 1894 | G23: =G3+G9 -> 2010 | H23: =H3+H9 -> 2044 | I23: =I3+I9 -> 2282 | J23: =J3+J9 -> 2482 | ... AL23: =AL3+AL9 -> 19234
A25: Kapitalbedarf Monat 1-6 vor GZ | C25: =SUM(C23:H23) -> 1727
A31: Profit / Loss | C31: =C27+C23 -> -1689 | D31: =D27+D23 -> -1296 | E31: =E27+E23 -> -1236 | F31: =F27+F23 -> 1894 | G31: =G27+G23 -> 2010 | H31: =H27+H23 -> 2044 | I31: =I27+I23 -> 2282 | J31: =J27+J23 -> 2482 | ... AL31: =AL27+AL23 -> 19234
A33: Kapitalbedarf Monat 1-6 nach GZ | C33: =SUM(C31:H31) -> 1727
A34: Kapitalbedarf Monat 7-12 nach GZ | C34: =SUM(I31:N31) -> 17050
A35: Lebenshaltungskosten / Gehalt | C35: 4000
A38: Inputs
A39: Calculations
A40: Outputs
A41: Actuals
A42: Scenarios
A43: External
A44: Warnings

Sheet Umsatz
D1: 46112 | E1: =EOMONTH(D1,1) -> 46142 | F1: =EOMONTH(E1,1) -> 46173 | G1: =EOMONTH(F1,1) -> 46203 | H1: =EOMONTH(G1,1) -> 46234 | I1: =EOMONTH(H1,1) -> 46265 | J1: =EOMONTH(I1,1) -> 46295 | K1: =EOMONTH(J1,1) -> 46326 | L1: =EOMONTH(K1,1) -> 46356 | ... AM1: =EOMONTH(AL1,1) -> 47177
A3: Total Revenue | D3: =D5+D28 -> 220 | E3: =E5+E28 -> 340 | F3: =F5+F28 -> 560 | G3: =G5+G28 -> 3880 | H3: =H5+H28 -> 4220 | I3: =I5+I28 -> 4560 | J3: =J5+J28 -> 5020 | K3: =K5+K28 -> 5400 | ... AM3: =AM5+AM28 -> 45640
A5: Digital Service Revenue | D5: =SUM(D16,D23) -> 220 | E5: =SUM(E16,E23) -> 340 | F5: =SUM(F16,F23) -> 560 | G5: =SUM(G16,G23) -> 880 | H5: =SUM(H16,H23) -> 1220 | I5: =SUM(I16,I23) -> 1560 | J5: =SUM(J16,J23) -> 2020 | K5: =SUM(K16,K23) -> 2400 | ... AM5: =SUM(AM16,AM23) -> 42640
B7: Revenue - Free Users | D7: 0 | E7: 0 | F7: 0 | G7: 0 | H7: 0 | I7: 0 | J7: 0 | K7: 0 | L7: 0 | M7: 0 | N7: 0 | O7: 0 | P7: 0 | Q7: 0 | R7: 0 | S7: 0 | T7: 0 | U7: 0 | V7: 0 | W7: 0 | X7: 0 | Y7: 0 | Z7: 0 | AA7: 0 | AB7: 0 | AC7: 0 | AD7: 0 | AE7: 0 | AF7: 0 | AG7: 0 | AH7: 0 | AI7: 0 | AJ7: 0 | AK7: 0 | AL7: 0 | AM7: 0
B8: # users free | C8: 0 | D8: =D9 -> 30 | E8: =D8+E9 -> 60 | F8: =E8+F9 -> 91 | G8: =F8+G9 -> 147 | H8: =G8+H9 -> 206 | I8: =H8+I9 -> 267 | J8: =I8+J9 -> 332 | K8: =J8+K9 -> 400 | L8: =K8+L9 -> 472 | ... AM8: =AL8+AM9 -> 7112
B9: # new users (from Wachstum) | D9: =Wachstum!D18 -> 30 | E9: =Wachstum!E18 -> 30 | F9: =Wachstum!F18 -> 31 | G9: =Wachstum!G18 -> 56 | H9: =Wachstum!H18 -> 59 | I9: =Wachstum!I18 -> 61 | J9: =Wachstum!J18 -> 65 | K9: =Wachstum!K18 -> 68 | ... AM9: =Wachstum!AM18 -> 655
B10: # active free users | D10: =D9 -> 30 | E10: =SUM(D9:E9) -> 60 | F10: =SUM(D9:F9) -> 91 | G10: =SUM(E9:G9) -> 117 | H10: =SUM(F9:H9) -> 146 | I10: =SUM(G9:I9) -> 176 | J10: =SUM(H9:J9) -> 185 | K10: =SUM(I9:K9) -> 194 | L10: =SUM(J9:L9) -> 205 | M10: =SUM(K9:M9) -> 216 | ... AM10: =SUM(AK9:AM9) -> 1770
B12: Monthly Growth | D12: =D13 -> 1 | E12: =IF(E13<>"", E13,D12) -> 1 | F12: =IF(F13<>"", F13,E12) -> 1 | G12: =IF(G13<>"", G13,F12) -> 1 | H12: =IF(H13<>"", H13,G12) -> 1 | I12: =IF(I13<>"", I13,H12) -> 1 | J12: =IF(J13<>"", J13,I12) -> 1 | K12: =IF(K13<>"", K13,J12) -> 1 | L12: =IF(L13<>"", L13,K12) -> 1 | ... AM12: =IF(AM13<>"", AM13,AL12) -> 1
B13: Monthly Growth - Adjustment | D13: 1 | G13: 1 | J13: 1 | M13: 1
B14: Monthly Churn | D14: 0.01
B16: Revenue - Paid Users | C16: 20 | D16: =D17*$C16 -> 120 | E16: =E17*$C16 -> 240 | F16: =F17*$C16 -> 360 | G16: =G17*$C16 -> 580 | H16: =H17*$C16 -> 820 | I16: =I17*$C16 -> 1060 | J16: =J17*$C16 -> 1320 | K16: =K17*$C16 -> 1600 | ... AM16: =AM17*$C16 -> 28440
B17: # users paid | D17: =ROUND(D8*$C18,0) -> 6 | E17: =ROUND(E8*$C18,0) -> 12 | F17: =ROUND(F8*$C18,0) -> 18 | G17: =ROUND(G8*$C18,0) -> 29 | H17: =ROUND(H8*$C18,0) -> 41 | I17: =ROUND(I8*$C18,0) -> 53 | J17: =ROUND(J8*$C18,0) -> 66 | K17: =ROUND(K8*$C18,0) -> 80 | ... AM17: =ROUND(AM8*$C18,0) -> 1422
B18: Share of Paid users | C18: 0.2
B21: COST | D21: =Kosten!E11 -> 48 | E21: =Kosten!F11 -> 96 | F21: =Kosten!G11 -> 144 | G21: =Kosten!H11 -> 232 | H21: =Kosten!I11 -> 328 | I21: =Kosten!J11 -> 424 | J21: =Kosten!K11 -> 528 | K21: =Kosten!L11 -> 640 | ... AM21: =Kosten!AN11 -> 11376
B23: Revenue - Premium Users | D23: =D24*$C24 -> 100 | E23: =E24*$C24 -> 100 | F23: =F24*$C24 -> 200 | G23: =G24*$C24 -> 300 | H23: =H24*$C24 -> 400 | I23: =I24*$C24 -> 500 | J23: =J24*$C24 -> 700 | K23: =K24*$C24 -> 800 | ... AM23: =AM24*$C24 -> 14200
B24: #users premium | C24: 100 | D24: =ROUND(D17*$C25,0) -> 1 | E24: =ROUND(E17*$C25,0) -> 1 | F24: =ROUND(F17*$C25,0) -> 2 | G24: =ROUND(G17*$C25,0) -> 3 | H24: =ROUND(H17*$C25,0) -> 4 | I24: =ROUND(I17*$C25,0) -> 5 | J24: =ROUND(J17*$C25,0) -> 7 | K24: =ROUND(K17*$C25,0) -> 8 | ... AM24: =ROUND(AM17*$C25,0) -> 142
B25: Share of Premium users | C25: 0.1
A28: Consulting Revenue | D28: =$C30*D31 -> 0 | E28: =$C30*E31 -> 0 | F28: =$C30*F31 -> 0 | G28: =$C30*G31 -> 3000 | H28: =$C30*H31 -> 3000 | I28: =$C30*I31 -> 3000 | J28: =$C30*J31 -> 3000 | K28: =$C30*K31 -> 3000 | ... AM28: =$C30*AM31 -> 3000
A30: Day Rate | C30: 1500
A31: # Paid days / month | D31: 0 | E31: 0 | F31: 0 | G31: 2 | H31: 2 | I31: 2 | J31: 2 | K31: 2 | L31: 2 | M31: 2 | N31: 2 | O31: 2 | P31: 2 | Q31: 2 | R31: 2 | S31: 2 | T31: 2 | U31: 2 | V31: 2 | W31: 2 | X31: 2 | Y31: 2 | Z31: 2 | AA31: 2 | AB31: 2 | AC31: 2 | AD31: 2 | AE31: 2 | AF31: 2 | AG31: 2 | AH31: 2 | AI31: 2 | AJ31: 2 | AK31: 2 | AL31: 2 | AM31: 2
A1004: Revenue

Sheet Wachstum
D1: 46112 | E1: =EOMONTH(D1,1) -> 46142 | F1: =EOMONTH(E1,1) -> 46173 | G1: =EOMONTH(F1,1) -> 46203 | H1: =EOMONTH(G1,1) -> 46234 | I1: =EOMONTH(H1,1) -> 46265 | J1: =EOMONTH(I1,1) -> 46295 | K1: =EOMONTH(J1,1) -> 46326 | L1: =EOMONTH(K1,1) -> 46356 | ... AM1: =EOMONTH(AL1,1) -> 47177
A2: Monat # | D2: 1 | E2: 2 | F2: 3 | G2: 4 | H2: 5 | I2: 6 | J2: 7 | K2: 8 | L2: 9 | M2: 10 | N2: 11 | O2: 12 | P2: 13 | Q2: 14 | R2: 15 | S2: 16 | T2: 17 | U2: 18 | V2: 19 | W2: 20 | X2: 21 | Y2: 22 | Z2: 23 | AA2: 24 | AB2: 25 | AC2: 26 | AD2: 27 | AE2: 28 | AF2: 29 | AG2: 30 | AH2: 31 | AI2: 32 | AJ2: 33 | AK2: 34 | AL2: 35 | AM2: 36
A4: Events and direct reachout
B5: Neu | D5: 30 | E5: =D5 -> 30 | F5: =E5 -> 30 | G5: =F5 -> 30 | H5: =G5 -> 30 | I5: =H5 -> 30 | J5: =I5 -> 30 | K5: =J5 -> 30 | L5: =K5 -> 30 | ... AM5: =AL5 -> 30
B6: Kummuliert | D6: =D5 -> 30 | E6: =E5+D6 -> 60 | F6: =F5+E6 -> 90 | G6: =G5+F6 -> 120 | H6: =H5+G6 -> 150 | I6: =I5+H6 -> 180 | J6: =J5+I6 -> 210 | K6: =K5+J6 -> 240 | L6: =L5+K6 -> 270 | ... AM6: =AM5+AL6 -> 1080
A9: WOM Rate (pro Nutzer/Monat) | D9: 1.0% | E9: 1.1% | F9: 1.1% | G9: 1.2% | H9: 1.2% | I9: 1.3% | J9: 1.3% | K9: 1.4% | L9: 1.5% | M9: 1.6% | N9: 1.6% | O9: 1.7% | P9: 1.8% | Q9: 1.9% | R9: 2.0% | S9: 2.1% | T9: 2.2% | U9: 2.3% | V9: 2.4% | W9: 2.5% | X9: 2.7% | Y9: 2.8% | Z9: 2.9% | AA9: 3.1% | AB9: 3.2% | AC9: 3.4% | AD9: 3.6% | AE9: 3.7% | AF9: 3.9% | AG9: 4.1% | AH9: 4.3% | AI9: 4.5% | AJ9: 4.8% | AK9: 5.0% | AL9: 5.3% | AM9: 5.5%
B10: WOM – Neue Nutzer | D10: 0 | E10: 0 | F10: 1 | G10: 1 | H10: 2 | I10: 2 | J10: 3 | K10: 4 | L10: 5 | M10: 6 | N10: 7 | O10: 8 | P10: 10 | Q10: 12 | R10: 14 | S10: 16 | T10: 19 | U10: 23 | V10: 26 | W10: 31 | X10: 36 | Y10: 42 | Z10: 48 | AA10: 56 | AB10: 65 | AC10: 75 | AD10: 87 | AE10: 101 | AF10: 117 | AG10: 135 | AH10: 156 | AI10: 181 | AJ10: 210 | AK10: 244 | AL10: 283 | AM10: 329
B11: WOM – Kumuliert | D11: 0 | E11: =E10+D11 -> 0 | F11: =F10+E11 -> 1 | G11: =G10+F11 -> 2 | H11: =H10+G11 -> 4 | I11: =I10+H11 -> 6 | J11: =J10+I11 -> 9 | K11: =K10+J11 -> 13 | L11: =L10+K11 -> 18 | ... AM11: =AM10+AL11 -> 2355
A13: Blog / Social / Website
B14: Neu | D14: 0 | E14: 0 | F14: 0 | G14: 25 | H14: 27 | I14: 29 | J14: 32 | K14: 34 | L14: 37 | M14: 40 | N14: 43 | O14: 47 | P14: 50 | Q14: 54 | R14: 59 | S14: 63 | T14: 69 | U14: 74 | V14: 80 | W14: 86 | X14: 93 | Y14: 101 | Z14: 109 | AA14: 117 | AB14: 127 | AC14: 137 | AD14: 148 | AE14: 160 | AF14: 173 | AG14: 186 | AH14: 201 | AI14: 217 | AJ14: 235 | AK14: 254 | AL14: 274 | AM14: 296
B15: Kummuliert | D15: =D14 -> 0 | E15: =E14+D15 -> 0 | F15: =F14+E15 -> 0 | G15: =G14+F15 -> 25 | H15: =H14+G15 -> 52 | I15: =I14+H15 -> 81 | J15: =J14+I15 -> 113 | K15: =K14+J15 -> 147 | L15: =L14+K15 -> 184 | ... AM15: =AM14+AL15 -> 3677
A18: Total – Neue Nutzer | D18: =SUM(D14,D10,D5,) -> 30 | E18: =SUM(E14,E10,E5,) -> 30 | F18: =SUM(F14,F10,F5,) -> 31 | G18: =SUM(G14,G10,G5,) -> 56 | H18: =SUM(H14,H10,H5,) -> 59 | I18: =SUM(I14,I10,I5,) -> 61 | J18: =SUM(J14,J10,J5,) -> 65 | K18: =SUM(K14,K10,K5,) -> 68 | ... AM18: =SUM(AM14,AM10,AM5,) -> 655
A19: Total Nutzer (kumuliert) | D19: =D18 -> 30 | E19: =E18+D19 -> 60 | F19: =F18+E19 -> 91 | G19: =G18+F19 -> 147 | H19: =H18+G19 -> 206 | I19: =I18+H19 -> 267 | J19: =J18+I19 -> 332 | K19: =K18+J19 -> 400 | L19: =L18+K19 -> 472 | ... AM19: =AM18+AL19 -> 7112
A23: Direktansprachen - kalt
A24: Affiliate marketing
A30: Assumptions
A31: Referrals is a significant share of the growth
A32: Public Founder Journey generates visitors
A33: Events create frequent user intakes
A35: Types of sources
A36: Organic - social
A37: Events
A38: Referrals
A39: Paid
A47: Friends and Family
... A50: Late Majority

Sheet Kosten
E1: 46112 | F1: =EOMONTH(E1,1) -> 46142 | G1: =EOMONTH(F1,1) -> 46173 | H1: =EOMONTH(G1,1) -> 46203 | I1: =EOMONTH(H1,1) -> 46234 | J1: =EOMONTH(I1,1) -> 46265 | K1: =EOMONTH(J1,1) -> 46295 | L1: =EOMONTH(K1,1) -> 46326 | M1: =EOMONTH(L1,1) -> 46356 | ... AN1: =EOMONTH(AM1,1) -> 47177
A3: Total | E3: =SUM(E5,E16,E23,E27,E41) -> -1909 | F3: =SUM(F5,F16,F23,F27,F41) -> -1636 | G3: =SUM(G5,G16,G23,G27,G41) -> -1796 | H3: =SUM(H5,H16,H23,H27,H41) -> -1986 | I3: =SUM(I5,I16,I23,I27,I41) -> -2210 | J3: =SUM(J5,J16,J23,J27,J41) -> -2516 | K3: =SUM(K5,K16,K23,K27,K41) -> -2738 | L3: =SUM(L5,L16,L23,L27,L41) -> -2918 | ... AN3: =SUM(AN5,AN16,AN23,AN27,AN41) -> -26406
A5: Variable Kosten | E5: =-SUM(E7:E12) -> -158 | F5: =-SUM(F7:F12) -> -266 | G5: =-SUM(G7:G12) -> -426 | H5: =-SUM(H7:H12) -> -616 | I5: =-SUM(I7:I12) -> -820 | J5: =-SUM(J7:J12) -> -1026 | K5: =-SUM(K7:K12) -> -1248 | L5: =-SUM(L7:L12) -> -1428 | ... AN5: =-SUM(AN7:AN12) -> -22016
B7: Affiliate Marketing
D9: AI cost / user
B10: Free | D10: 2 | E10: =$D10*Umsatz!D10 -> 60 | F10: =$D10*Umsatz!E10 -> 120 | G10: =$D10*Umsatz!F10 -> 182 | H10: =$D10*Umsatz!G10 -> 234 | I10: =$D10*Umsatz!H10 -> 292 | J10: =$D10*Umsatz!I10 -> 352 | K10: =$D10*Umsatz!J10 -> 370 | L10: =$D10*Umsatz!K10 -> 388 | ... AN10: =$D10*Umsatz!AM10 -> 3540
B11: Paid | D11: 0.4 | E11: =Umsatz!D16*$D11 -> 48 | F11: =Umsatz!E16*$D11 -> 96 | G11: =Umsatz!F16*$D11 -> 144 | H11: =Umsatz!G16*$D11 -> 232 | I11: =Umsatz!H16*$D11 -> 328 | J11: =Umsatz!I16*$D11 -> 424 | K11: =Umsatz!J16*$D11 -> 528 | L11: =Umsatz!K16*$D11 -> 640 | ... AN11: =Umsatz!AM16*$D11 -> 11376
B12: Premium | D12: 0.5 | E12: =$D12*Umsatz!D23 -> 50 | F12: =$D12*Umsatz!E23 -> 50 | G12: =$D12*Umsatz!F23 -> 100 | H12: =$D12*Umsatz!G23 -> 150 | I12: =$D12*Umsatz!H23 -> 200 | J12: =$D12*Umsatz!I23 -> 250 | K12: =$D12*Umsatz!J23 -> 350 | L12: =$D12*Umsatz!K23 -> 400 | ... AN12: =$D12*Umsatz!AM23 -> 7100
B14: Verkaufs- & Steuerabwicklungsgebühren (Merchant of Record) | D14: 0.05 | E14: =$D14*Umsatz!D5 -> 11 | F14: =$D14*Umsatz!E5 -> 17 | G14: =$D14*Umsatz!F5 -> 28 | H14: =$D14*Umsatz!G5 -> 44 | I14: =$D14*Umsatz!H5 -> 61 | J14: =$D14*Umsatz!I5 -> 78 | K14: =$D14*Umsatz!J5 -> 101 | L14: =$D14*Umsatz!K5 -> 120 | ... AN14: =$D14*Umsatz!AM5 -> 2132
A16: Produktentwicklung | E16: =-SUM(E17:E22) -> -1200 | F16: =-SUM(F17:F22) -> -1200 | G16: =-SUM(G17:G22) -> -1200 | H16: =-SUM(H17:H22) -> -1200 | I16: =-SUM(I17:I22) -> -1200 | J16: =-SUM(J17:J22) -> -1200 | K16: =-SUM(K17:K22) -> -1200 | L16: =-SUM(L17:L22) -> -1200 | ... AL16: =-SUM(AL17:AL22) -> -1200
B17: Quellcode Verwaltung Github | E17: 20 | F17: 20 | G17: 20 | H17: 20 | I17: 20 | J17: 20 | K17: 20 | L17: 20 | M17: 20 | N17: 20 | O17: 20 | P17: 20 | Q17: 20 | R17: 20 | S17: 20 | T17: 20 | U17: 20 | V17: 20 | W17: 20 | X17: 20 | Y17: 20 | Z17: 20 | AA17: 20 | AB17: 20 | AC17: 20 | AD17: 20 | AE17: 20 | AF17: 20 | AG17: 20 | AH17: 20 | AI17: 20 | AJ17: 20 | AK17: 20 | AL17: 20 | AM17: 20 | AN17: 20
B18: Coding Agent: Claude Code | E18: 100 | F18: 100 | G18: 100 | H18: 100 | I18: 100 | J18: 100 | K18: 100 | L18: 100 | M18: 100 | N18: 100 | O18: 100 | P18: 100 | Q18: 100 | R18: 100 | S18: 100 | T18: 100 | U18: 100 | V18: 100 | W18: 100 | X18: 100 | Y18: 100 | Z18: 100 | AA18: 100 | AB18: 100 | AC18: 100 | AD18: 100 | AE18: 100 | AF18: 100 | AG18: 100 | AH18: 100 | AI18: 100 | AJ18: 100 | AK18: 100 | AL18: 100 | AM18: 100 | AN18: 100
B19: Coding IDE: Cursor | E19: 60 | F19: 60 | G19: 60 | H19: 60 | I19: 60 | J19: 60 | K19: 60 | L19: 60 | M19: 60 | N19: 60 | O19: 60 | P19: 60 | Q19: 60 | R19: 60 | S19: 60 | T19: 60 | U19: 60 | V19: 60 | W19: 60 | X19: 60 | Y19: 60 | Z19: 60 | AA19: 60 | AB19: 60 | AC19: 60 | AD19: 60 | AE19: 60 | AF19: 60 | AG19: 60 | AH19: 60 | AI19: 60 | AJ19: 60 | AK19: 60 | AL19: 60 | AM19: 60 | AN19: 60
B20: KI Protoyping: Lovable | E20: 20 | F20: 20 | G20: 20 | H20: 20 | I20: 20 | J20: 20 | K20: 20 | L20: 20 | M20: 20 | N20: 20 | O20: 20 | P20: 20 | Q20: 20 | R20: 20 | S20: 20 | T20: 20 | U20: 20 | V20: 20 | W20: 20 | X20: 20 | Y20: 20 | Z20: 20 | AA20: 20 | AB20: 20 | AC20: 20 | AD20: 20 | AE20: 20 | AF20: 20 | AG20: 20 | AH20: 20 | AI20: 20 | AJ20: 20 | AK20: 20 | AL20: 20 | AM20: 20 | AN20: 20
B21: Rechenleistung für KI Training | E21: 1000 | F21: 1000 | G21: 1000 | H21: 1000 | I21: 1000 | J21: 1000 | K21: 1000 | L21: 1000 | M21: 1000 | N21: 1000 | O21: 1000 | P21: 1000 | Q21: 1000 | R21: 1000 | S21: 1000 | T21: 1000 | U21: 1000 | V21: 1000 | W21: 1000 | X21: 1000 | Y21: 1000 | Z21: 1000 | AA21: 1000 | AB21: 1000 | AC21: 1000 | AD21: 1000 | AE21: 1000 | AF21: 1000 | AG21: 1000 | AH21: 1000 | AI21: 1000 | AJ21: 1000 | AK21: 1000 | AL21: 1000 | AM21: 1000 | AN21: 1000
A23: IT Infrastruktur | E23: =-SUM(E24:E26) -> -100 | F23: =-SUM(F24:F26) -> -100 | G23: =-SUM(G24:G26) -> -100 | H23: =-SUM(H24:H26) -> -100 | I23: =-SUM(I24:I26) -> -120 | J23: =-SUM(J24:J26) -> -220 | K23: =-SUM(K24:K26) -> -220 | L23: =-SUM(L24:L26) -> -220 | ... AN23: =-SUM(AN24:AN26) -> -220
B24: Hosting (Hetzner, AWS) | E24: 100 | F24: 100 | G24: 100 | H24: 100 | I24: 100 | J24: 200 | K24: 200 | L24: 200 | M24: 200 | N24: 200 | O24: 200 | P24: 200 | Q24: 200 | R24: 200 | S24: 200 | T24: 200 | U24: 200 | V24: 200 | W24: 200 | X24: 200 | Y24: 200 | Z24: 200 | AA24: 200 | AB24: 200 | AC24: 200 | AD24: 200 | AE24: 200 | AF24: 200 | AG24: 200 | AH24: 200 | AI24: 200 | AJ24: 200 | AK24: 200 | AL24: 200 | AM24: 200 | AN24: 200
B25: Sentry (Application Monitoring) | E25: 0 | F25: 0 | G25: 0 | H25: 0 | I25: 20 | J25: 20 | K25: 20 | L25: 20 | M25: 20 | N25: 20 | O25: 20 | P25: 20 | Q25: 20 | R25: 20 | S25: 20 | T25: 20 | U25: 20 | V25: 20 | W25: 20 | X25: 20 | Y25: 20 | Z25: 20 | AA25: 20 | AB25: 20 | AC25: 20 | AD25: 20 | AE25: 20 | AF25: 20 | AG25: 20 | AH25: 20 | AI25: 20 | AJ25: 20 | AK25: 20 | AL25: 20 | AM25: 20 | AN25: 20
H26: ´
A27: Administrative Kosten | E27: =-SUM(E28:E40) -> -411 | F27: =-SUM(F28:F40) -> -30 | G27: =-SUM(G28:G40) -> -30 | H27: =-SUM(H28:H40) -> -30 | I27: =-SUM(I28:I40) -> -30 | J27: =-SUM(J28:J40) -> -30 | K27: =-SUM(K28:K40) -> -30 | L27: =-SUM(L28:L40) -> -30 | ... AN27: =-SUM(AN28:AN40) -> -4130
B28: Kontoführung | E28: 10 | F28: 10 | G28: 10 | H28: 10 | I28: 10 | J28: 10 | K28: 10 | L28: 10 | M28: 10 | N28: 10 | O28: 10 | P28: 10 | Q28: 10 | R28: 10 | S28: 10 | T28: 10 | U28: 10 | V28: 10 | W28: 10 | X28: 10 | Y28: 10 | Z28: 10 | AA28: 10 | AB28: 10 | AC28: 10 | AD28: 10 | AE28: 10 | AF28: 10 | AG28: 10 | AH28: 10 | AI28: 10 | AJ28: 10 | AK28: 10 | AL28: 10 | AM28: 10 | AN28: 10
B29: Steuerberater
B30: One Stop Shop - EU Steueranmeldung (taxdoo)
B31: Email & Office | E31: 20 | F31: 20 | G31: 20 | H31: 20 | I31: 20 | J31: 20 | K31: 20 | L31: 20 | M31: 20 | N31: 20 | O31: 20 | P31: 20 | Q31: 20 | R31: 20 | S31: 20 | T31: 20 | U31: 20 | V31: 20 | W31: 20 | X31: 20 | Y31: 20 | Z31: 20 | AA31: 20 | AB31: 20 | AC31: 20 | AD31: 20 | AE31: 20 | AF31: 20 | AG31: 20 | AH31: 20 | AI31: 20 | AJ31: 20 | AK31: 20 | AL31: 20 | AM31: 20 | AN31: 20
B32: Berufshaftpflichtversicherung (exali.de) | E32: 321 | Q32: 321 | AC32: 321
C33: Brutto | E33: 0 | F33: 0 | G33: 0 | H33: 0 | I33: 0 | J33: 0 | K33: 0 | L33: 0 | M33: 0 | N33: 0 | O33: 0 | P33: 0 | Q33: 4000 | R33: 4000 | S33: 4000 | T33: 4000 | U33: 4000 | V33: 4000 | W33: 4000 | X33: 4000 | Y33: 4000 | Z33: 4000 | AA33: 4000 | AB33: 4000 | AC33: 4000 | AD33: 4000 | AE33: 4000 | AF33: 4000 | AG33: 4000 | AH33: 4000 | AI33: 4000 | AJ33: 4000 | AK33: 4000 | AL33: 4000 | AM33: 4000 | AN33: 4000
B35: Gewerbeanmeldung | E35: 60
B36: Equipment für Gründung (private Einlage)
B37: Equipment nachkauf
B38: IHK Beitrag | G38: 0 | P38: 0 | AB38: 100 | AN38: 100
B39: Reisen und Events
A41: Marketing Kosten | E41: =-SUM(E42:E45) -> -40 | F41: =-SUM(F42:F45) -> -40 | G41: =-SUM(G42:G45) -> -40 | H41: =-SUM(H42:H45) -> -40 | I41: =-SUM(I42:I45) -> -40 | J41: =-SUM(J42:J45) -> -40 | K41: =-SUM(K42:K45) -> -40 | L41: =-SUM(L42:L45) -> -40 | ... AN41: =-SUM(AN42:AN45) -> -40
A42: ChatGPT | E42: 20 | F42: 20 | G42: 20 | H42: 20 | I42: 20 | J42: 20 | K42: 20 | L42: 20 | M42: 20 | N42: 20 | O42: 20 | P42: 20 | Q42: 20 | R42: 20 | S42: 20 | T42: 20 | U42: 20 | V42: 20 | W42: 20 | X42: 20 | Y42: 20 | Z42: 20 | AA42: 20 | AB42: 20 | AC42: 20 | AD42: 20 | AE42: 20 | AF42: 20 | AG42: 20 | AH42: 20 | AI42: 20 | AJ42: 20 | AK42: 20 | AL42: 20 | AM42: 20 | AN42: 20
A43: Gemini | E43: 20 | F43: 20 | G43: 20 | H43: 20 | I43: 20 | J43: 20 | K43: 20 | L43: 20 | M43: 20 | N43: 20 | O43: 20 | P43: 20 | Q43: 20 | R43: 20 | S43: 20 | T43: 20 | U43: 20 | V43: 20 | W43: 20 | X43: 20 | Y43: 20 | Z43: 20 | AA43: 20 | AB43: 20 | AC43: 20 | AD43: 20 | AE43: 20 | AF43: 20 | AG43: 20 | AH43: 20 | AI43: 20 | AJ43: 20 | AK43: 20 | AL43: 20 | AM43: 20 | AN43: 20
A44: Website Hosting
A48: Personalkosten | E48: =-SUM(E49:E52) -> -40 | F48: =-SUM(F49:F52) -> -40 | G48: =-SUM(G49:G52) -> -40 | H48: =-SUM(H49:H52) -> -40 | I48: =-SUM(I49:I52) -> -40 | J48: =-SUM(J49:J52) -> -40 | K48: =-SUM(K49:K52) -> -40 | L48: =-SUM(L49:L52) -> -40 | ... AN48: =-SUM(AN49:AN52) -> -40
A49: Unternehmerlohn | C49: Brutto | E49: 20 | F49: 20 | G49: 20 | H49: 20 | I49: 20 | J49: 20 | K49: 20 | L49: 20 | M49: 20 | N49: 20 | O49: 20 | P49: 20 | Q49: 20 | R49: 20 | S49: 20 | T49: 20 | U49: 20 | V49: 20 | W49: 20 | X49: 20 | Y49: 20 | Z49: 20 | AA49: 20 | AB49: 20 | AC49: 20 | AD49: 20 | AE49: 20 | AF49: 20 | AG49: 20 | AH49: 20 | AI49: 20 | AJ49: 20 | AK49: 20 | AL49: 20 | AM49: 20 | AN49: 20
E50: 20 | F50: 20 | G50: 20 | H50: 20 | I50: 20 | J50: 20 | K50: 20 | L50: 20 | M50: 20 | N50: 20 | O50: 20 | P50: 20 | Q50: 20 | R50: 20 | S50: 20 | T50: 20 | U50: 20 | V50: 20 | W50: 20 | X50: 20 | Y50: 20 | Z50: 20 | AA50: 20 | AB50: 20 | AC50: 20 | AD50: 20 | AE50: 20 | AF50: 20 | AG50: 20 | AH50: 20 | AI50: 20 | AJ50: 20 | AK50: 20 | AL50: 20 | AM50: 20 | AN50: 20

Sheet Private Finanzen
C1: 2026 | D1: 2027 | E1: 2028 | F1: 2029
A2: Einnahmen außerhalb der Selbständigkeit (monatlich) | C2: =SUM(C3:C12) -> 7004 | D2: =SUM(D3:D12) -> 7004 | E2: =SUM(E3:E12) -> 7004 | F2: =SUM(F3:F12) -> 7004
B3: Nettogehalt Ehe- bzw. Lebenspartner/in | C3: 4000 | D3: 4000 | E3: 4000 | F3: 4000
B4: Anderer Nettolohn/-gehaltseinnahmen | C4: n/a | D4: n/a | E4: n/a | F4: n/a
B5: Kindergeld | C5: 510 | D5: 510 | E5: 510 | F5: 510
B6: Erziehungsgeld | C6: n/a | D6: n/a | E6: n/a | F6: n/a
B7: Unterhalt | C7: n/a | D7: n/a | E7: n/a | F7: n/a
B8: Vermietung Badstr. | C8: 1750 | D8: 1750 | E8: 1750 | F8: 1750
B9: Vermietung Paul Küstner | C9: 544 | D9: 544 | E9: 544 | F9: 544
B10: Einkommen aus Kapitalerträgen | C10: 200 | D10: 200 | E10: 200 | F10: 200
B11: Sonstige Einnahmen außerhalb der Selbständigkeit | C11: n/a | D11: n/a | E11: n/a | F11: n/a
A13: Privatausgaben (monatlich) | C13: =-SUM(C14:C32) -> -11100.26 | D13: =-SUM(D14:D32) -> -10863.01 | E13: =-SUM(E14:E32) -> -10863.01 | F13: =-SUM(F14:F32) -> -10844.26
B14: Private Wohnkosten (inkl. Nebenkosten und Strom) | C14: 150 | D14: 150 | E14: 150 | F14: 150
B15: Kranken- und Pflegeversicherung | C15: =350+400 -> 750 | D15: =350+400 -> 750 | E15: =350+400 -> 750 | F15: =350+400 -> 750
B16: Rentenversicherung/Altersvorsorge | C16: 600 | D16: 600 | E16: 600 | F16: 600
B17: Arbeitslosenversicherung | C17: n/a | D17: n/a | E17: n/a | F17: n/a
B18: Sonstige Versicherungen (Berufsunfähigkeit, Haftpflicht, Hausrat, Unfallversicherung etc.) | C18: 100 | D18: 100 | E18: 100 | F18: 100
B19: Private Kfz-Kosten | C19: 400 | D19: 400 | E19: 400 | F19: 400
B20: Telefon/Fernsehen/Radio/Internet | C20: 150 | D20: 150 | E20: 150 | F20: 150
B21: Beiträge (Vereine etc.) | C21: 10 | D21: 10 | E21: 10 | F21: 10
B22: Haushaltsnahe Dienstleistungen | C22: 500 | D22: 500 | E22: 500 | F22: 500
B23: Kosten des täglichen Bedarfs (Essen, Trinken, Kleidung etc.) | C23: 1800 | D23: 1800 | E23: 1800 | F23: 1800
B25: Unterhaltszahlungen an andere | C25: n/a | D25: n/a | E25: n/a | F25: n/a
B26: Anschaffungen Haus | C26: 1000 | D26: 1000 | E26: 1000 | F26: 1000
B27: Urlaub | C27: 400 | D27: 400 | E27: 400 | F27: 400
B28: Hausgeld, Tilgung und Zinsen Badstr | C28: =1423.75 + 559 -> 1982.75 | D28: =1423.75 + 559 -> 1982.75 | E28: =1423.75 + 559 -> 1982.75 | F28: =1423.75 + 559 -> 1982.75
B29: Hausgeld Paul Küstner | C29: 297.26 | D29: 297.26 | E29: 297.26 | F29: 297.26
B30: Tilgung und Zinsen Wohnhaus | C30: 2300 | D30: 2300 | E30: 2300 | F30: 2300
B31: Kita Julian | C31: =268+75 -> 343 | D31: =348+75 -> 423 | E31: =348+75 -> 423 | F31: =348+75*3/4 -> 404.25
B32: Kita Frederik | C32: =(348+75)*3/4 -> 317.25 | D32: 0 | E32: 0 | F32: 0
A34: Rücklagen (jährlich)
A35: Rücklage für Einkommensteuer
A37: Benötigte Privatentnahme aus der Unternehmung (monatlich) | C37: =C2+C13 -> -4096.26 | D37: =D2+D13 -> -3859.01 | E37: =E2+E13 -> -3859.01 | F37: =F2+F13 -> -3840.26

Sheet Liquidität
A8: Private Einlagen
A9: Private Entnahme Unternehmer

Sheet Annahmen
A1: ID | B1: Assumption
A2: 1 | B2: Fair usage caps cost of external models for providing the service Assumption, x% of paid plan | C2: 0.5
A3: 2 | B3: Consulting can only start with sufficient users
A4: 3

Sheet Research
